dsdk/__init__.py
dsdk/asset.py
dsdk/flowsheet.py
dsdk/interval.py
dsdk/model.py
dsdk/mssql.py
dsdk/persistor.py
dsdk/postgres.py
dsdk/service.py
dsdk/utils.py
dsdk-2.2.2.dist-info/METADATA
dsdk-2.2.2.dist-info/WHEEL
dsdk-2.2.2.dist-info/top_level.txt
dsdk-2.2.2.dist-info/RECORD
