Metadata-Version: 2.1
Name: dsdk
Version: 2.2.2
Summary: An opinionated library to help deploy data science projects
Author-email: Jason Lubken <jlubken@users.noreply.github.com>, Michael Becker <mdbecker@users.noreply.github.com>, Corey Chivers <cjbayesian@user.noreply.github.com>, Graydon Neill <grayeye@user.noreply.github.com>, Penn Signals <pennsignals@pennmedicine.upenn.edu>
License: MIT License
Project-URL: Homepage, https://github.com/pennsignals/dsdk
Project-URL: Source, https://github.com/pennsignals/dsdk
Project-URL: Tracker, https://github.com/pennsignals/dsdk/issues
Classifier: Development Status :: 5 - Production/Stable
Classifier: Intended Audience :: Developers
Classifier: License :: OSI Approved :: MIT License
Classifier: Operating System :: Unix
Classifier: Operating System :: POSIX
Classifier: Programming Language :: Python :: 3.9
Classifier: Programming Language :: Python :: 3.10
Classifier: Programming Language :: Python :: 3.11
Classifier: Programming Language :: Python :: 3.12
Classifier: Programming Language :: Python :: Implementation :: CPython
Classifier: Topic :: Utilities
Requires-Python: >=3.9
Requires-Dist: blosc>=1.10.6
Requires-Dist: cfgenvy>=2.2.2
Requires-Dist: numpy>=1.15.4
Requires-Dist: pandas>=0.23.4
Requires-Dist: requests>=2.26.0
Requires-Dist: urllib3<2; python_version < "3.10"
Requires-Dist: urllib3>=2; python_version >= "3.10"
Provides-Extra: dev
Requires-Dist: astroid; extra == "dev"
Requires-Dist: black; extra == "dev"
Requires-Dist: coverage[toml]; extra == "dev"
Requires-Dist: cython>=3.0.11; extra == "dev"
Requires-Dist: flake8; extra == "dev"
Requires-Dist: flake8-bugbear; extra == "dev"
Requires-Dist: flake8-commas; extra == "dev"
Requires-Dist: flake8-comprehensions; extra == "dev"
Requires-Dist: flake8-docstrings; extra == "dev"
Requires-Dist: flake8-mutable; extra == "dev"
Requires-Dist: flake8-sorted-keys; extra == "dev"
Requires-Dist: isort; extra == "dev"
Requires-Dist: mypy; extra == "dev"
Requires-Dist: pep8-naming; extra == "dev"
Requires-Dist: pre-commit; extra == "dev"
Requires-Dist: psycopg2-binary>=2.9.9; extra == "dev"
Requires-Dist: pylint; extra == "dev"
Requires-Dist: pymssql>=2.3.0; extra == "dev"
Requires-Dist: pytest; extra == "dev"
Requires-Dist: pytest-cov; extra == "dev"
Requires-Dist: types-pymssql; extra == "dev"
Requires-Dist: types-python-dateutil; extra == "dev"
Requires-Dist: types-pyyaml; extra == "dev"
Requires-Dist: types-requests; extra == "dev"
Requires-Dist: vcrpy; extra == "dev"
Provides-Extra: psycopg2
Requires-Dist: psycopg2-binary>=2.9.9; extra == "psycopg2"
Provides-Extra: pymssql
Requires-Dist: cython>=3.0.11; extra == "pymssql"
Requires-Dist: pymssql>=2.3.0; extra == "pymssql"
